breakthrough/__init__.py
breakthrough-0.0.1.dist-info/LICENSE
breakthrough-0.0.1.dist-info/METADATA
breakthrough-0.0.1.dist-info/WHEEL
breakthrough-0.0.1.dist-info/top_level.txt
breakthrough-0.0.1.dist-info/RECORD
