Metadata-Version: 2.1
Name: breakthrough
Version: 0.0.1
Summary: A library for creating breakthrough innovation in AI
Home-page: https://github.com/sahagar/Breakthrough
Author: Sahaj Agarwal
Author-email: sahagar@microsoft.com
License: UNKNOWN
Keywords: python,ai,breakthrough
Platform: UNKNOWN
Classifier: Programming Language :: Python :: 3
Classifier: License :: OSI Approved :: MIT License
Classifier: Operating System :: OS Independent
Requires-Python: >=3.6
License-File: LICENSE
